lins_sms/__init__.py
lins_sms/apps.py
lins_sms/mensagem_sms.py
lins_sms/models/__init__.py
lins_sms/models/mensagem_sms.py
lins_sms-1.0.3.2.dist-info/METADATA
lins_sms-1.0.3.2.dist-info/WHEEL
lins_sms-1.0.3.2.dist-info/top_level.txt
lins_sms-1.0.3.2.dist-info/RECORD
