Metadata-Version: 2.1
Name: lins-sms
Version: 1.0.3.2
Summary: Pacote de envio de sms
Home-page: https://bitbucket.org/grupolinsferrao/pypck-lins_sms/
Author: Halyson Sampaio
Author-email: halyson@lojaspompeia.com.br
License: MIT
Platform: UNKNOWN
